pygridmappr/__init__.py
pygridmappr/core.py
pygridmappr/utils.py
pygridmappr-0.1.1.dist-info/licenses/LICENSE
pygridmappr-0.1.1.dist-info/METADATA
pygridmappr-0.1.1.dist-info/WHEEL
pygridmappr-0.1.1.dist-info/top_level.txt
pygridmappr-0.1.1.dist-info/RECORD
