Metadata-Version: 2.4
Name: pygridmappr
Version: 0.1.1
Summary: Python implementation of R package gridmappr for automated gridmap layout generation
Home-page: https://github.com/tmfnk/pygridmappr
Author: Python port of gridmappr by Roger Beecham
Author-email: 
License: AGPL-3.0-or-later
Project-URL: Bug Reports, https://github.com/tmfnk/pygridmappr/issues
Project-URL: Source, https://github.com/tmfnk/pygridmappr
Project-URL: Original R Package, https://github.com/rogerbeecham/gridmappr
Keywords: gridmap,tilemaps,cartography,geovisualization,small-multiples,assignment-problem,hungarian-algorithm
Classifier: Development Status :: 4 - Beta
Classifier: Intended Audience :: Science/Research
Classifier: Topic :: Scientific/Engineering :: GIS
Classifier: Topic :: Scientific/Engineering :: Visualization
Classifier: License :: OSI Approved :: GNU Affero General Public License v3 or later (AGPLv3+)
Classifier: Programming Language :: Python :: 3
Classifier: Programming Language :: Python :: 3.7
Classifier: Programming Language :: Python :: 3.8
Classifier: Programming Language :: Python :: 3.9
Classifier: Programming Language :: Python :: 3.10
Classifier: Programming Language :: Python :: 3.11
Requires-Python: >=3.7
License-File: LICENSE
Requires-Dist: numpy>=1.19.0
Requires-Dist: pandas>=1.1.0
Requires-Dist: scipy>=1.5.0
Requires-Dist: matplotlib>=3.3.0
Provides-Extra: dev
Requires-Dist: pytest>=6.0; extra == "dev"
Requires-Dist: pytest-cov>=2.10; extra == "dev"
Requires-Dist: black>=21.0; extra == "dev"
Requires-Dist: flake8>=3.9; extra == "dev"
Requires-Dist: jupyter>=1.0; extra == "dev"
Dynamic: author
Dynamic: classifier
Dynamic: description
Dynamic: description-content-type
Dynamic: home-page
Dynamic: keywords
Dynamic: license
Dynamic: license-file
Dynamic: project-url
Dynamic: provides-extra
Dynamic: requires-dist
Dynamic: requires-python
Dynamic: summary
